jsonfaker/__init__.py
jsonfaker/faker.py
jsonfaker/helper.py
jsonfaker/utils.py
modelmock/__init__.py
modelmock/faker.py
modelmock/utils.py
modelmock-0.1.1.dist-info/LICENSE.txt
modelmock-0.1.1.dist-info/METADATA
modelmock-0.1.1.dist-info/WHEEL
modelmock-0.1.1.dist-info/top_level.txt
modelmock-0.1.1.dist-info/RECORD
